MofanJiqiXuexiXilieJiaocheng20201031Fix1/README.md
MofanJiqiXuexiXilieJiaocheng20201031Fix1/__init__.py
MofanJiqiXuexiXilieJiaocheng20201031Fix1/__main__.py
MofanJiqiXuexiXilieJiaocheng20201031Fix1/file.epub
MofanJiqiXuexiXilieJiaocheng20201031Fix1/index.html
MofanJiqiXuexiXilieJiaocheng20201031Fix1/css/__init__.py
MofanJiqiXuexiXilieJiaocheng20201031Fix1/css/annotations.css
MofanJiqiXuexiXilieJiaocheng20201031Fix1/css/main.css
MofanJiqiXuexiXilieJiaocheng20201031Fix1/css/normalize.css
MofanJiqiXuexiXilieJiaocheng20201031Fix1/css/popup.css
MofanJiqiXuexiXilieJiaocheng20201031Fix1/font/__init__.py
MofanJiqiXuexiXilieJiaocheng20201031Fix1/font/fontello.eot
MofanJiqiXuexiXilieJiaocheng20201031Fix1/font/fontello.svg
MofanJiqiXuexiXilieJiaocheng20201031Fix1/font/fontello.ttf
MofanJiqiXuexiXilieJiaocheng20201031Fix1/font/fontello.woff
MofanJiqiXuexiXilieJiaocheng20201031Fix1/img/__init__.py
MofanJiqiXuexiXilieJiaocheng20201031Fix1/img/annotator-glyph-sprite.png
MofanJiqiXuexiXilieJiaocheng20201031Fix1/img/annotator-icon-sprite.png
MofanJiqiXuexiXilieJiaocheng20201031Fix1/img/apple-touch-icon.png
MofanJiqiXuexiXilieJiaocheng20201031Fix1/img/cancelfullscreen.png
MofanJiqiXuexiXilieJiaocheng20201031Fix1/img/close.png
MofanJiqiXuexiXilieJiaocheng20201031Fix1/img/fullscreen.png
MofanJiqiXuexiXilieJiaocheng20201031Fix1/img/loader.gif
MofanJiqiXuexiXilieJiaocheng20201031Fix1/img/menu-icon.png
MofanJiqiXuexiXilieJiaocheng20201031Fix1/img/save.png
MofanJiqiXuexiXilieJiaocheng20201031Fix1/img/saved.png
MofanJiqiXuexiXilieJiaocheng20201031Fix1/img/settings-s.png
MofanJiqiXuexiXilieJiaocheng20201031Fix1/img/settings.png
MofanJiqiXuexiXilieJiaocheng20201031Fix1/img/star.png
MofanJiqiXuexiXilieJiaocheng20201031Fix1/js/__init__.py
MofanJiqiXuexiXilieJiaocheng20201031Fix1/js/epub.js
MofanJiqiXuexiXilieJiaocheng20201031Fix1/js/epub.min.js
MofanJiqiXuexiXilieJiaocheng20201031Fix1/js/epub.min.map
MofanJiqiXuexiXilieJiaocheng20201031Fix1/js/hooks.min.js
mofan_jiqi_xuexi_xilie_jiaocheng_2020_10_31_fix1-2025.3.24.0.dist-info/METADATA
mofan_jiqi_xuexi_xilie_jiaocheng_2020_10_31_fix1-2025.3.24.0.dist-info/WHEEL
mofan_jiqi_xuexi_xilie_jiaocheng_2020_10_31_fix1-2025.3.24.0.dist-info/entry_points.txt
mofan_jiqi_xuexi_xilie_jiaocheng_2020_10_31_fix1-2025.3.24.0.dist-info/top_level.txt
mofan_jiqi_xuexi_xilie_jiaocheng_2020_10_31_fix1-2025.3.24.0.dist-info/RECORD
